sentry_nodestore_elastic/__init__.py
sentry_nodestore_elastic/backend.py
sentry_nodestore_elastic-1.0.2.dist-info/LICENSE
sentry_nodestore_elastic-1.0.2.dist-info/METADATA
sentry_nodestore_elastic-1.0.2.dist-info/WHEEL
sentry_nodestore_elastic-1.0.2.dist-info/top_level.txt
sentry_nodestore_elastic-1.0.2.dist-info/RECORD
