Metadata-Version: 2.2
Name: sentry-nodestore-elastic
Version: 1.0.2
Summary: Sentry nodestore Elasticsearch backend
Home-page: https://github.com/andrsp/sentry-nodestore-elastic
Author: andrsp@gmail.com
Author-email: andrsp@gmail.com
License: Apache-2.0
Project-URL: Bug Tracker, https://github.com/andrsp/sentry-nodestore-elastic/issues
Project-URL: CI, https://github.com/andrsp/sentry-nodestore-elastic/actions
Project-URL: Source Code, https://github.com/andrsp/sentry-nodestore-elastic
Keywords: sentry,elasticsearch,nodestore,backend
Classifier: Development Status :: 5 - Production/Stable
Classifier: Intended Audience :: Developers
Classifier: Operating System :: POSIX
Classifier: Operating System :: MacOS :: MacOS X
Classifier: Operating System :: Microsoft :: Windows
Classifier: Programming Language :: Python
Classifier: Operating System :: OS Independent
License-File: LICENSE
Requires-Dist: sentry==25.*
Requires-Dist: elasticsearch==8.*
Dynamic: author
Dynamic: author-email
Dynamic: classifier
Dynamic: description
Dynamic: description-content-type
Dynamic: home-page
Dynamic: keywords
Dynamic: license
Dynamic: project-url
Dynamic: requires-dist
Dynamic: summary
